clacks/__init__.py
clacks/components.py
clacks/db.py
clacks/gettext.py
clacks/models.py
clacks/tools.py
clacks/_grants/corecms.py
clacks/_shim/access_grants.py
clacks/_shim/gtfile.py
clacks/_shim/http_range.py
clacks/_shim/i18n_tool.py
clacks/_shim/sqlalchemy.py
clacks/cmd/clacks.py
clacks/component/Component.py
clacks/component/cClientLogin.py
clacks/component/cRootMenu2.py
clacks/core/BasePage.py
clacks/core/CPage.py
clacks/core/Cache.py
clacks/core/Configuration.py
clacks/core/LDAPSession.py
clacks/core/__init__.py
clacks/core/env.py
clacks/core/templates.py
clacks/core/url.py
clacks/generators/cms.py
clacks/handlers/AdminPage.py
clacks/handlers/ArticleHandler.py
clacks/handlers/ArticlelistHandler.py
clacks/handlers/BoxesV1.py
clacks/handlers/ControlsAppendableV1.py
clacks/handlers/ControlsV1.py
clacks/handlers/FileManagerPage.py
clacks/handlers/GrantsV1.py
clacks/handlers/JScriptI18n.py
clacks/handlers/LanguagesV1.py
clacks/handlers/PageStylesV1.py
clacks/handlers/PagesFilterV1.py
clacks/handlers/RestUserCurrent.py
clacks/handlers/SessionV1.py
clacks/handlers/SiteNodePlacementsV1.py
clacks/handlers/SiteNodeTemplatesV1.py
clacks/handlers/SiteNodesV1.py
clacks/handlers/URLHandler.py
clacks/handlers/URLMapper.py
clacks/handlers/UserGrantsV1.py
clacks/handlers/UserNotificationsV1.py
clacks/handlers/UserStatsV1.py
clacks/handlers/UsersNamesV1.py
clacks/handlers/UsersV1.py
clacks/i18n/__init__.py
clacks/i18n/mo2json.py
clacks/model/Address.py
clacks/model/ArticleListNode.py
clacks/model/ArticleNode.py
clacks/model/Base.py
clacks/model/Box.py
clacks/model/BoxControl.py
clacks/model/Client.py
clacks/model/Control.py
clacks/model/ControlProperty.py
clacks/model/DbFeature.py
clacks/model/Grant.py
clacks/model/HeadNode.py
clacks/model/Language.py
clacks/model/LinkNode.py
clacks/model/MailAbuse.py
clacks/model/MetaNode.py
clacks/model/MultiBoxControl.py
clacks/model/NodeGrantsControl.py
clacks-0.1.1.dev845.dist-info/DESCRIPTION.rst
clacks-0.1.1.dev845.dist-info/METADATA
clacks-0.1.1.dev845.dist-info/RECORD
clacks-0.1.1.dev845.dist-info/WHEEL
clacks-0.1.1.dev845.dist-info/entry_points.txt
clacks-0.1.1.dev845.dist-info/metadata.json
clacks-0.1.1.dev845.dist-info/top_level.txt
