Metadata-Version: 2.0
Name: clacks
Version: 0.1.1.dev845
Summary: Clacks framework
Home-page: https://codewedo.com/
Author: Code We Do Ltd
Author-email: support@codewedo.com
License: GPLv3
Platform: Linux
Classifier: Development Status :: 2 - Pre-Alpha
Classifier: Environment :: Web Environment
Classifier: Intended Audience :: Developers
Classifier: Operating System :: Unix
Classifier: Programming Language :: Python :: 3.5
Classifier: Topic :: Internet :: WWW/HTTP
Classifier: Topic :: Internet :: WWW/HTTP :: Dynamic Content
Classifier: Topic :: Internet :: WWW/HTTP :: WSGI
Classifier: Topic :: Software Development :: Libraries :: Python Modules
Requires-Dist: alembic (==0.9.1)
Requires-Dist: babel (==2.4.0)
Requires-Dist: chameleon (==3.1)
Requires-Dist: cherrypy (>=10.2.1)
Requires-Dist: coverage (>=4.3.4)
Requires-Dist: flup6 (==1.1.1)
Requires-Dist: ldap3 (==2.2.2)
Requires-Dist: lingua (>=4.12)
Requires-Dist: pip (==9.0.1)
Requires-Dist: polib (==1.0.8)
Requires-Dist: psycopg2 (>=2.7.1)
Requires-Dist: pyicu (==1.9.5)
Requires-Dist: python-dateutil (==2.6.0)
Requires-Dist: pytz (>=2017.2)
Requires-Dist: requests (==2.13.0)
Requires-Dist: ruamel.yaml (>=0.14.5)
Requires-Dist: setproctitle (==1.1.10)
Requires-Dist: setuptools (>=34.4.0)
Requires-Dist: sqlalchemy (==1.1.9)
Requires-Dist: tzlocal (==1.3)
Requires-Dist: wheel (==0.29.0)
